voxel/__init__.py
voxel/config.py
voxel/device.py
voxel/med_volume.py
voxel/numpy_routines.py
voxel/orientation.py
voxel/experimental/__init__.py
voxel/experimental/plot.py
voxel/io/__init__.py
voxel/io/dicom.py
voxel/io/format_io.py
voxel/io/http.py
voxel/io/nifti.py
voxel/utils/__init__.py
voxel/utils/collect_env.py
voxel/utils/env.py
voxel/utils/logger.py
voxel/utils/pixel_data.py
pyvoxel-0.0.2.dist-info/LICENSE
pyvoxel-0.0.2.dist-info/METADATA
pyvoxel-0.0.2.dist-info/WHEEL
pyvoxel-0.0.2.dist-info/top_level.txt
pyvoxel-0.0.2.dist-info/RECORD
