Metadata-Version: 2.1
Name: pyvoxel
Version: 0.0.2
Summary: An AI-powered open-source medical image analysis toolbox
Home-page: https://github.com/pyvoxel/pyvoxel
Author: Arjun Desai
License: GNU
Project-URL: Documentation, https://pyvoxel.readthedocs.io/
Classifier: Programming Language :: Python :: 3
Classifier: License :: OSI Approved :: GNU General Public License v3 (GPLv3)
Classifier: Operating System :: OS Independent
Requires-Python: >=3.6
License-File: LICENSE
Requires-Dist: dataclasses (>=0.6)
Requires-Dist: numpy
Requires-Dist: natsort
Requires-Dist: nibabel
Requires-Dist: packaging
Requires-Dist: pydicom (>=1.6.0)
Requires-Dist: PyYAML (>=5.4.1)
Requires-Dist: requests
Requires-Dist: tabulate
Requires-Dist: termcolor
Requires-Dist: tqdm (>=4.42.0)
Provides-Extra: dev
Requires-Dist: simpleitk ; extra == 'dev'
Requires-Dist: sigpy ; extra == 'dev'
Requires-Dist: h5py ; extra == 'dev'
Requires-Dist: coverage ; extra == 'dev'
Requires-Dist: flake8 ; extra == 'dev'
Requires-Dist: flake8-bugbear ; extra == 'dev'
Requires-Dist: flake8-comprehensions ; extra == 'dev'
Requires-Dist: isort ; extra == 'dev'
Requires-Dist: black (==22.8.0) ; extra == 'dev'
Requires-Dist: click (==8.0.2) ; extra == 'dev'
Requires-Dist: pytest-cov (>=2.10.1) ; extra == 'dev'
Requires-Dist: pre-commit (>=2.9.3) ; extra == 'dev'
Requires-Dist: requests-mock ; extra == 'dev'
Requires-Dist: parameterized ; extra == 'dev'
Requires-Dist: twine ; extra == 'dev'
Provides-Extra: docs
Requires-Dist: mistune (<2.0.0,>=0.8.1) ; extra == 'docs'
Requires-Dist: sphinx ; extra == 'docs'
Requires-Dist: sphinxcontrib.bibtex ; extra == 'docs'
Requires-Dist: m2r2 ; extra == 'docs'
